scdrs/__init__.py
scdrs/data_loader.py
scdrs/method.py
scdrs/pp.py
scdrs/util.py
scdrs/version.py
scdrs/data/gwas_gene.from_pval.gs
scdrs/data/gwas_gene.from_zscore.gs
scdrs/data/gwas_gene.gs
scdrs/data/gwas_gene.pval_file
scdrs/data/gwas_gene.zscore_file
scdrs/data/mouse_human_homologs.txt
scdrs/data/toydata_gs_mouse.ref_Ctrl20_CovConstCovariate.full_score.gz
scdrs/data/toydata_gs_mouse.ref_Ctrl20_CovConstCovariate.scdrs_cell_corr
scdrs/data/toydata_gs_mouse.ref_Ctrl20_CovConstCovariate.scdrs_gene
scdrs/data/toydata_gs_mouse.ref_Ctrl20_CovConstCovariate.scdrs_group.cell_type
scdrs/data/toydata_gs_mouse.ref_Ctrl20_CovConstCovariate.score.gz
scdrs/data/toydata_gs_mouse.ref_Ctrl20_CovNone.score.gz
scdrs/data/toydata_human.gs
scdrs/data/toydata_mouse.cov
scdrs/data/toydata_mouse.gs
scdrs/data/toydata_mouse.h5ad
scdrs-1.0.2.data/scripts/scdrs
scdrs-1.0.2.dist-info/LICENSE
scdrs-1.0.2.dist-info/METADATA
scdrs-1.0.2.dist-info/WHEEL
scdrs-1.0.2.dist-info/top_level.txt
scdrs-1.0.2.dist-info/RECORD
