Metadata-Version: 2.1
Name: scdrs
Version: 1.0.2
Summary: Single-cell disease-relevance score
Home-page: https://github.com/martinjzhang/scDRS
Author: Martin Jinye Zhang, Kangcheng Hou
Author-email: martinjzhang@gmail.com, kangchenghou@gmail.com
Classifier: Programming Language :: Python :: 3
Classifier: License :: OSI Approved :: MIT License
Classifier: Operating System :: OS Independent
Requires-Python: >=3.5
License-File: LICENSE
Requires-Dist: numpy (>=1.19.0)
Requires-Dist: pandas (>=1.0.0)
Requires-Dist: scipy (>=1.5.0)
Requires-Dist: scanpy (>=1.6.0)
Requires-Dist: anndata (>=0.7)
Requires-Dist: scikit-misc (>=0.1.3)
Requires-Dist: statsmodels (>=0.11.0)
Requires-Dist: tqdm
Requires-Dist: fire (>=0.4.0)
Requires-Dist: pytest (>=6.2.0)
